bandersnatch_vrfs-0.6.1.dist-info/METADATA
bandersnatch_vrfs-0.6.1.dist-info/WHEEL
bandersnatch_vrfs-0.6.1.dist-info/licenses/LICENSE
bandersnatch_vrfs.libs/libgcc_s-0366c7ba.so.1
bandersnatch_vrfs/__init__.py
bandersnatch_vrfs/bandersnatch_vrfs.pypy310-pp73-arm-linux-gnu.so
bandersnatch_vrfs-0.6.1.dist-info/RECORD
