Metadata-Version: 2.4
Name: bandersnatch_vrfs
Version: 0.6.1
Classifier: Programming Language :: Rust
Classifier: Programming Language :: Python :: Implementation :: CPython
Classifier: Programming Language :: Python :: Implementation :: PyPy
License-File: LICENSE
Summary: Python Bandersnatch VRFs library utilizing the RUST ark-ec-vrfs cryptographic library
Home-Page: https://github.com/JAMdotTech/py-bandersnatch-vrfs
Author-email: JAMdot Technologies <devops@jamdot.tech>
Requires-Python: >=3.9
